htmlxword/cli.py
htmlxword/htmlxword.py
htmlxword/staticgen.py
htmlxword/data/config.yaml
htmlxword/data/csstemplate.css
htmlxword/data/html_xword_template.html
htmlxword/data/jstemplate.js
htmlxword-0.0.8.dist-info/LICENSE
htmlxword-0.0.8.dist-info/METADATA
htmlxword-0.0.8.dist-info/WHEEL
htmlxword-0.0.8.dist-info/entry_points.txt
htmlxword-0.0.8.dist-info/top_level.txt
htmlxword-0.0.8.dist-info/RECORD
