Metadata-Version: 2.1
Name: htmlxword
Version: 0.0.8
Summary: Create Static HTML/Js Crosswords
Project-URL: github, https://github.com/trisdav/htmlxword/tree/main
License-File: LICENSE
Requires-Dist: genxword
